odoo/addons/event_session_registration_multi_qty/README.rst
odoo/addons/event_session_registration_multi_qty/__init__.py
odoo/addons/event_session_registration_multi_qty/__manifest__.py
odoo/addons/event_session_registration_multi_qty/i18n/event_session_registration_multi_qty.pot
odoo/addons/event_session_registration_multi_qty/i18n/it.po
odoo/addons/event_session_registration_multi_qty/models/__init__.py
odoo/addons/event_session_registration_multi_qty/models/event_session.py
odoo/addons/event_session_registration_multi_qty/readme/CONTRIBUTORS.rst
odoo/addons/event_session_registration_multi_qty/readme/DESCRIPTION.rst
odoo/addons/event_session_registration_multi_qty/readme/USAGE.rst
odoo/addons/event_session_registration_multi_qty/static/description/icon.png
odoo/addons/event_session_registration_multi_qty/static/description/index.html
odoo/addons/event_session_registration_multi_qty/tests/__init__.py
odoo/addons/event_session_registration_multi_qty/tests/test_event_session_registration_multi_qty.py
odoo12_addon_event_session_registration_multi_qty-12.0.1.0.0.99.dev7.dist-info/METADATA
odoo12_addon_event_session_registration_multi_qty-12.0.1.0.0.99.dev7.dist-info/WHEEL
odoo12_addon_event_session_registration_multi_qty-12.0.1.0.0.99.dev7.dist-info/top_level.txt
odoo12_addon_event_session_registration_multi_qty-12.0.1.0.0.99.dev7.dist-info/RECORD
